acton_ai/__init__.py
acton_ai/connection_utilities.py
acton_ai/controller_wrapper.py
acton_ai/joint.py
acton_ai/logger.py
acton_ai/mover_wrapper.py
acton_ai/scripts/calibrate_robot.py
acton_ai/scripts/teleop.py
acton_ai/scripts/validate_robot.py
acton_ai-0.4.0.dist-info/METADATA
acton_ai-0.4.0.dist-info/WHEEL
acton_ai-0.4.0.dist-info/entry_points.txt
acton_ai-0.4.0.dist-info/RECORD
