Metadata-Version: 2.1
Name: acton_ai
Version: 0.4.0
Summary: My reppolicies for robot arms, and making them useful with multi-modal LLMs.
License: Proprietary
Author: apockill
Author-email: apocthiel@gmail.com
Requires-Python: >=3.10,<4.0
Classifier: License :: Other/Proprietary License
Classifier: Programming Language :: Python :: 3
Classifier: Programming Language :: Python :: 3.10
Classifier: Programming Language :: Python :: 3.11
Classifier: Programming Language :: Python :: 3.12
Classifier: Programming Language :: Python :: 3.13
Requires-Dist: opencv-python (>=4.10.0.84,<5.0.0.0)
Requires-Dist: pymycobot (>=3.6.7,<4.0.0)
